h2rs/__init__.py
h2rs/__main__.py
h2rs/h2rs.py
h2rs/h2rscmd.py
h2rs-0.0.1.dist-info/LICENSE
h2rs-0.0.1.dist-info/METADATA
h2rs-0.0.1.dist-info/WHEEL
h2rs-0.0.1.dist-info/entry_points.txt
h2rs-0.0.1.dist-info/top_level.txt
h2rs-0.0.1.dist-info/RECORD
