Metadata-Version: 2.1
Name: h2rs
Version: 0.0.1
Summary: Detects request smuggling via HTTP/2 downgrades.
Home-page: https://github.com/riramar/h2rs/
Author: Ricardo Iramar dos Santos
Author-email: ricardo.iramar@gmail.com
License: UNKNOWN
Project-URL: Bug Tracker, https://github.com/riramar/h2rs/issues
Platform: UNKNOWN
Classifier: Programming Language :: Python :: 3
Classifier: License :: OSI Approved :: GNU General Public License v2 (GPLv2)
Classifier: Operating System :: OS Independent
Requires-Python: >=3.6
License-File: LICENSE
Requires-Dist: certifi
Requires-Dist: h2
Requires-Dist: argparse
